hugep2g/__init__.py
hugep2g/cli.py
hugep2g/config.py
hugep2g/pipelines.py
hugep2g/versions.py
hugep2g/dep/genblasta/blosum62
hugep2g/dep/genblasta/genblasta_v1.0.4_linux_x86_64
hugep2g/dep/genblasta/genblasta_wu.py
hugep2g/dep/genblasta/perform.txt
hugep2g/dep/genblasta/tblastn
hugep2g/dep/genblasta/wu-blastall
hugep2g/dep/genblasta/xdformat
hugep2g/dep/wublast/COPYRIGHT
hugep2g/dep/wublast/FAQ-Indexing.html
hugep2g/dep/wublast/HISTORY
hugep2g/dep/wublast/LICENSE
hugep2g/dep/wublast/NCBI_BlastOutput.dtd
hugep2g/dep/wublast/NCBI_BlastOutput.mod
hugep2g/dep/wublast/NCBI_Entity.mod
hugep2g/dep/wublast/README.html
hugep2g/dep/wublast/WHOAMI
hugep2g/dep/wublast/ab-blastall
hugep2g/dep/wublast/ab-formatdb
hugep2g/dep/wublast/blast3.pe.linux26-x64.tar.gz
hugep2g/dep/wublast/blasta
hugep2g/dep/wublast/blastn
hugep2g/dep/wublast/blastp
hugep2g/dep/wublast/blastx
hugep2g/dep/wublast/blosum62
hugep2g/dep/wublast/gb2fasta
hugep2g/dep/wublast/gt2fasta
hugep2g/dep/wublast/md5.pe.linux26-x64
hugep2g/dep/wublast/memfile
hugep2g/dep/wublast/memory.html
hugep2g/dep/wublast/nrdb
hugep2g/dep/wublast/pam
hugep2g/dep/wublast/parameters.html
hugep2g/dep/wublast/patdb
hugep2g/dep/wublast/pir2fasta
hugep2g/dep/wublast/pressdb
hugep2g/dep/wublast/psoutput.html
hugep2g/dep/wublast/setdb
hugep2g/dep/wublast/sp2fasta
hugep2g/dep/wublast/sysblast.sample
hugep2g/dep/wublast/tabular.html
hugep2g/dep/wublast/tblastn
hugep2g/dep/wublast/tblastx
hugep2g/dep/wublast/xdformat
hugep2g/dep/wublast/xdget
hugep2g/dep/wublast/filter/README
hugep2g/dep/wublast/filter/dust
hugep2g/dep/wublast/filter/nmerge
hugep2g/dep/wublast/filter/nseg
hugep2g/dep/wublast/filter/pmerge
hugep2g/dep/wublast/filter/pseg
hugep2g/dep/wublast/filter/seg
hugep2g/dep/wublast/filter/seg+xnu
hugep2g/dep/wublast/filter/xnu
hugep2g/dep/wublast/filter/xnu+seg
hugep2g/dep/wublast/matrix/README
hugep2g/dep/wublast/matrix/aa/blosum100
hugep2g/dep/wublast/matrix/aa/blosum30
hugep2g/dep/wublast/matrix/aa/blosum35
HugeP2G-1.0.4.dist-info/LICENSE
HugeP2G-1.0.4.dist-info/METADATA
HugeP2G-1.0.4.dist-info/WHEEL
HugeP2G-1.0.4.dist-info/entry_points.txt
HugeP2G-1.0.4.dist-info/top_level.txt
HugeP2G-1.0.4.dist-info/RECORD
