Metadata-Version: 2.1
Name: HugeP2G
Version: 1.0.4
Summary: Aligning a large number of protein sequences to a genome (use genblasta and genewise)
Home-page: https://github.com/SouthernCD/HugeP2G
Author: Yuxing Xu
Author-email: xuyuxing@mail.kib.ac.cn
Requires-Python: >=3.5
License-File: LICENSE
Requires-Dist: yxalign
Requires-Dist: yxseq
Requires-Dist: yxmath
Requires-Dist: yxutil
Requires-Dist: bcbio-gff >=0.6.6
Requires-Dist: biopython >=1.76
Requires-Dist: interlap >=0.2.6
Requires-Dist: pyfaidx >=0.5.5.2
